[
{"title": [], "link": ["http://www.chinadmoz.org/city/232/t1/o5/p1/"], "desc": ["\r\n\t\t", "\r\n\t\t\r\n\t\t"]},
{"title": [], "link": [], "desc": ["\u6392\u5e8f\u65b9\u5f0f:"]},
{"title": ["DMOZRank"], "link": ["http://www.chinadmoz.org/city/232/t0/o0/"], "desc": []},
{"title": ["\u6700\u65b0\u52a0\u5165"], "link": ["http://www.chinadmoz.org/city/232/t0/o5/"], "desc": []},
{"title": ["\u5165\u7ad9\u6d41\u91cf"], "link": ["http://www.chinadmoz.org/city/232/t0/o1/"], "desc": []},
{"title": ["\u51fa\u7ad9\u6d41\u91cf"], "link": ["http://www.chinadmoz.org/city/232/t0/o2/"], "desc": []},
{"title": ["PageRank"], "link": ["http://www.chinadmoz.org/city/232/t0/o3/"], "desc": []},
{"title": ["Alexa\u6392\u540d"], "link": ["http://www.chinadmoz.org/city/232/t0/o4/"], "desc": []}
]